{"region":"卡多尔","constellation":"梅戈","materials":{"稀有气体":{"max_output":26.48,"count":6,"records":[{"planet":"希罗德 八","richness":"完美","output":26.48},{"planet":"埃费恩的 二","richness":"富裕","output":18.94},{"planet":"希罗德 二","richness":"中等","output":16.18},{"planet":"罗密 五","richness":"中等","output":15.68},{"planet":"希罗德 七","richness":"贫瘠","output":13.5},{"planet":"罗密 三","richness":"中等","output":12.54}]},"反应金属":{"max_output":6.95,"count":3,"records":[{"planet":"希罗德 八","richness":"完美","output":6.95},{"planet":"罗密 七","richness":"富裕","output":4.65},{"planet":"埃费恩的 八","richness":"中等","output":4.03}]},"精密合金":{"max_output":17.01,"count":1,"records":[{"planet":"希罗德 六","richness":"中等","output":17.01}]},"纳米体":{"max_output":5.63,"count":2,"records":[{"planet":"艾哈拉勒 一","richness":"富裕","output":5.63},{"planet":"埃费恩的 一","richness":"富裕","output":4.76}]},"杂色复合物":{"max_output":21.63,"count":3,"records":[{"planet":"埃费恩的 二","richness":"富裕","output":21.63},{"planet":"罗密 二","richness":"中等","output":13.74},{"planet":"基恩瑟拉 三","richness":"贫瘠","output":11.91}]},"浓缩合金":{"max_output":21.77,"count":1,"records":[{"planet":"埃费恩的 五","richness":"富裕","output":21.77}]},"建筑模块":{"max_output":17.51,"count":1,"records":[{"planet":"基恩瑟拉 五","richness":"中等","output":17.51}]},"贵金属":{"max_output":22.2,"count":1,"records":[{"planet":"基恩瑟拉 三","richness":"富裕","output":22.2}]},"光泽合金":{"max_output":22.64,"count":35,"records":[{"planet":"希罗德 八","richness":"富裕","output":22.64},{"planet":"罗密 六","richness":"完美","output":21.22},{"planet":"罗密 四","richness":"富裕","output":20.31},{"planet":"基恩瑟拉 八","richness":"富裕","output":20.19},{"planet":"佐尔茨 八","richness":"富裕","output":19.42},{"planet":"罗密 五","richness":"富裕","output":18.8},{"planet":"基恩瑟拉 十一","richness":"富裕","output":18.34},{"planet":"埃费恩的 六","richness":"富裕","output":18.17},{"planet":"艾哈拉勒 四","richness":"中等","output":18.11},{"planet":"艾哈拉勒 五","richness":"中等","output":17.4},{"planet":"佐尔茨 七","richness":"富裕","output":17.29},{"planet":"基恩瑟拉 十","richness":"中等","output":17.09},{"planet":"罗密 七","richness":"富裕","output":16.67},{"planet":"德勒斯 一","richness":"中等","output":15.97},{"planet":"希罗德 一","richness":"中等","output":15.42},{"planet":"佐尔茨 二","richness":"中等","output":15.35},{"planet":"佐尔茨 五","richness":"中等","output":15.11},{"planet":"罗密 一","richness":"中等","output":14.87},{"planet":"佐尔茨 九","richness":"中等","output":14.79},{"planet":"佐尔茨 一","richness":"中等","output":14.59}]},"晶体复合物":{"max_output":15.29,"count":1,"records":[{"planet":"基恩瑟拉 六","richness":"中等","output":15.29}]},"等离子体团":{"max_output":1.48,"count":4,"records":[{"planet":"希罗德 二","richness":"富裕","output":1.48},{"planet":"希罗德 四","richness":"中等","output":1.04},{"planet":"罗密 二","richness":"富裕","output":1.02},{"planet":"希罗德 三","richness":"贫瘠","output":0.66}]},"硅结构铸材":{"max_output":6.96,"count":1,"records":[{"planet":"希罗德 五","richness":"贫瘠","output":6.96}]},"冷却剂":{"max_output":13.79,"count":2,"records":[{"planet":"基恩瑟拉 九","richness":"富裕","output":13.79},{"planet":"埃费恩的 七","richness":"富裕","output":12.37}]},"凝缩液":{"max_output":13.97,"count":3,"records":[{"planet":"埃费恩的 一","richness":"富裕","output":13.97},{"planet":"艾哈拉勒 一","richness":"中等","output":10.82},{"planet":"罗密 三","richness":"中等","output":10.6}]},"光滑复合物":{"max_output":24.21,"count":2,"records":[{"planet":"希罗德 七","richness":"富裕","output":24.21},{"planet":"艾哈拉勒 三","richness":"贫瘠","output":13.92}]},"光彩合金":{"max_output":16.48,"count":2,"records":[{"planet":"希罗德 八","richness":"中等","output":16.48},{"planet":"罗密 四","richness":"贫瘠","output":11.62}]},"有毒金属":{"max_output":3.07,"count":1,"records":[{"planet":"基恩瑟拉 七","richness":"贫瘠","output":3.07}]},"悬浮等离子":{"max_output":82.05,"count":6,"records":[{"planet":"基恩瑟拉 七","richness":"完美","output":82.05},{"planet":"埃费恩的 一","richness":"富裕","output":79.73},{"planet":"罗密 三","richness":"完美","output":78.9},{"planet":"基恩瑟拉 六","richness":"富裕","output":64.66},{"planet":"艾哈拉勒 一","richness":"中等","output":58.81},{"planet":"基恩瑟拉 五","richness":"中等","output":57.36}]},"黑暗复合物":{"max_output":13.92,"count":1,"records":[{"planet":"希罗德 四","richness":"贫瘠","output":13.92}]},"工业纤维":{"max_output":4.25,"count":5,"records":[{"planet":"希罗德 四","richness":"中等","output":4.25},{"planet":"希罗德 六","richness":"中等","output":4.05},{"planet":"希罗德 五","richness":"贫瘠","output":3.67},{"planet":"希罗德 三","richness":"贫瘠","output":3.32},{"planet":"希罗德 一","richness":"贫瘠","output":2.96}]},"纤维复合物":{"max_output":23.1,"count":4,"records":[{"planet":"艾哈拉勒 二","richness":"富裕","output":23.1},{"planet":"埃费恩的 六","richness":"完美","output":22.75},{"planet":"佐尔茨 七","richness":"富裕","output":19.02},{"planet":"罗密 六","richness":"富裕","output":17.86}]},"重水":{"max_output":183.17,"count":2,"records":[{"planet":"佐尔茨 十一","richness":"富裕","output":183.17},{"planet":"埃费恩的 五","richness":"中等","output":135.24}]},"离子溶液":{"max_output":6.05,"count":3,"records":[{"planet":"基恩瑟拉 八","richness":"中等","output":6.05},{"planet":"佐尔茨 六","richness":"中等","output":5.04},{"planet":"佐尔茨 十一","richness":"贫瘠","output":4.83}]},"液化臭氧":{"max_output":20.8,"count":2,"records":[{"planet":"佐尔茨 十一","richness":"富裕","output":20.8},{"planet":"埃费恩的 五","richness":"中等","output":17.05}]},"基础金属":{"max_output":6.1,"count":35,"records":[{"planet":"艾哈拉勒 三","richness":"富裕","output":6.1},{"planet":"基恩瑟拉 九","richness":"富裕","output":5.72},{"planet":"佐尔茨 六","richness":"完美","output":5.63},{"planet":"佐尔茨 八","richness":"完美","output":5.49},{"planet":"佐尔茨 七","richness":"富裕","output":5.22},{"planet":"基恩瑟拉 八","richness":"富裕","output":4.73},{"planet":"艾哈拉勒 五","richness":"中等","output":4.61},{"planet":"基恩瑟拉 十","richness":"中等","output":4.56},{"planet":"希罗德 六","richness":"中等","output":4.51},{"planet":"德勒斯 一","richness":"中等","output":4.44},{"planet":"佐尔茨 十","richness":"中等","output":4.23},{"planet":"佐尔茨 四","richness":"中等","output":4.19},{"planet":"基恩瑟拉 一","richness":"中等","output":4.11},{"planet":"罗密 一","richness":"中等","output":4.1},{"planet":"佐尔茨 二","richness":"中等","output":4.03},{"planet":"艾哈拉勒 二","richness":"中等","output":4.03},{"planet":"埃费恩的 六","richness":"中等","output":3.97},{"planet":"佐尔茨 五","richness":"中等","output":3.9},{"planet":"艾哈拉勒 四","richness":"中等","output":3.81},{"planet":"埃费恩的 八","richness":"中等","output":3.72}]},"聚芳酰胺":{"max_output":13.5,"count":2,"records":[{"planet":"佐尔茨 八","richness":"富裕","output":13.5},{"planet":"基恩瑟拉 十","richness":"富裕","output":12.62}]},"同位素燃料":{"max_output":1.82,"count":2,"records":[{"planet":"希罗德 三","richness":"贫瘠","output":1.82},{"planet":"希罗德 一","richness":"贫瘠","output":1.73}]}}}