{"region":"卡彻","constellation":"A-JI5E","materials":{"晶体复合物":{"max_output":37.15,"count":4,"records":[{"planet":"JA-O6J 六","richness":"完美","output":37.15},{"planet":"SNFV-I 十一","richness":"中等","output":25.24},{"planet":"SNFV-I 五","richness":"中等","output":20.4},{"planet":"L-B55M 三","richness":"贫瘠","output":17.37}]},"硅结构铸材":{"max_output":17.08,"count":8,"records":[{"planet":"CX65-5 三","richness":"完美","output":17.08},{"planet":"8B-2YA 六","richness":"富裕","output":14.99},{"planet":"L-B55M 八","richness":"中等","output":12.54},{"planet":"SNFV-I 一","richness":"贫瘠","output":9.37},{"planet":"8B-2YA 二","richness":"贫瘠","output":9.31},{"planet":"HP-64T 六","richness":"贫瘠","output":8.62},{"planet":"CX65-5 十","richness":"贫瘠","output":7.81},{"planet":"HP-64T 五","richness":"贫瘠","output":6.7}]},"稀有气体":{"max_output":30.7,"count":9,"records":[{"planet":"CX65-5 九","richness":"富裕","output":30.7},{"planet":"JA-O6J 九","richness":"富裕","output":28.43},{"planet":"JA-O6J 八","richness":"富裕","output":27.64},{"planet":"SNFV-I 九","richness":"富裕","output":27.32},{"planet":"CX65-5 八","richness":"富裕","output":27.02},{"planet":"L-B55M 七","richness":"中等","output":25.47},{"planet":"CX65-5 四","richness":"中等","output":24.1},{"planet":"HP-64T 四","richness":"贫瘠","output":18.66},{"planet":"JA-O6J 七","richness":"贫瘠","output":17.98}]},"精密合金":{"max_output":30.37,"count":8,"records":[{"planet":"L-B55M 九","richness":"富裕","output":30.37},{"planet":"JA-O6J 十二","richness":"富裕","output":29.11},{"planet":"SNFV-I 四","richness":"中等","output":23.4},{"planet":"HP-64T 六","richness":"中等","output":20.94},{"planet":"8B-2YA 八","richness":"贫瘠","output":17.54},{"planet":"8B-2YA 一","richness":"贫瘠","output":16.84},{"planet":"HP-64T 五","richness":"贫瘠","output":16.1},{"planet":"L-B55M 一","richness":"贫瘠","output":14.22}]},"有毒金属":{"max_output":7.99,"count":9,"records":[{"planet":"L-B55M 二","richness":"富裕","output":7.99},{"planet":"8B-2YA 四","richness":"富裕","output":7.03},{"planet":"SNFV-I 五","richness":"中等","output":6.47},{"planet":"SNFV-I 六","richness":"中等","output":6.19},{"planet":"JA-O6J 三","richness":"中等","output":5.87},{"planet":"JA-O6J 一","richness":"中等","output":5.82},{"planet":"JA-O6J 十","richness":"中等","output":5.28},{"planet":"JA-O6J 四","richness":"中等","output":5.26},{"planet":"SNFV-I 二","richness":"贫瘠","output":3.75}]},"光彩合金":{"max_output":34.73,"count":12,"records":[{"planet":"JA-O6J 二","richness":"完美","output":34.73},{"planet":"CX65-5 五","richness":"完美","output":31.9},{"planet":"V2-VC2 一","richness":"富裕","output":30.85},{"planet":"CX65-5 七","richness":"富裕","output":28.92},{"planet":"JA-O6J 七","richness":"中等","output":26.5},{"planet":"L-B55M 六","richness":"中等","output":24.23},{"planet":"SNFV-I 九","richness":"中等","output":21.98},{"planet":"CX65-5 六","richness":"中等","output":21.12},{"planet":"SNFV-I 十二","richness":"贫瘠","output":18.8},{"planet":"CX65-5 四","richness":"贫瘠","output":18.7},{"planet":"JA-O6J 五","richness":"贫瘠","output":18.48},{"planet":"HP-64T 三","richness":"贫瘠","output":16.94}]},"超张力塑料":{"max_output":22.9,"count":24,"records":[{"planet":"L-B55M 二","richness":"完美","output":22.9},{"planet":"JA-O6J 三","richness":"完美","output":22.26},{"planet":"L-B55M 四","richness":"富裕","output":21.03},{"planet":"L-B55M 九","richness":"富裕","output":20.57},{"planet":"JA-O6J 十二","richness":"富裕","output":20.19},{"planet":"SNFV-I 六","richness":"中等","output":16.27},{"planet":"8B-2YA 五","richness":"中等","output":16.19},{"planet":"8B-2YA 八","richness":"中等","output":16.16},{"planet":"SNFV-I 二","richness":"中等","output":16.0},{"planet":"8B-2YA 一","richness":"中等","output":15.37},{"planet":"JA-O6J 一","richness":"中等","output":14.15},{"planet":"L-B55M 一","richness":"中等","output":13.22},{"planet":"L-B55M 八","richness":"贫瘠","output":12.98},{"planet":"L-B55M 三","richness":"贫瘠","output":12.81},{"planet":"L-B55M 五","richness":"贫瘠","output":12.66},{"planet":"SNFV-I 四","richness":"贫瘠","output":12.36},{"planet":"CX65-5 一","richness":"贫瘠","output":12.36},{"planet":"V2-VC2 二","richness":"贫瘠","output":11.62},{"planet":"CX65-5 十","richness":"贫瘠","output":10.97},{"planet":"HP-64T 五","richness":"贫瘠","output":10.25}]},"纳米体":{"max_output":8.87,"count":2,"records":[{"planet":"JA-O6J 二","richness":"完美","output":8.87},{"planet":"HP-64T 二","richness":"中等","output":5.72}]},"活性气体":{"max_output":31.96,"count":20,"records":[{"planet":"HP-64T 二","richness":"完美","output":31.96},{"planet":"JA-O6J 九","richness":"富裕","output":30.85},{"planet":"HP-64T 四","richness":"富裕","output":30.48},{"planet":"JA-O6J 八","richness":"富裕","output":29.53},{"planet":"CX65-5 八","richness":"富裕","output":28.1},{"planet":"SNFV-I 十二","richness":"富裕","output":28.0},{"planet":"CX65-5 五","richness":"富裕","output":27.3},{"planet":"JA-O6J 五","richness":"富裕","output":26.88},{"planet":"L-B55M 六","richness":"中等","output":25.58},{"planet":"8B-2YA 七","richness":"中等","output":24.88},{"planet":"CX65-5 七","richness":"中等","output":24.46},{"planet":"CX65-5 九","richness":"中等","output":24.4},{"planet":"CX65-5 六","richness":"中等","output":23.64},{"planet":"SNFV-I 九","richness":"中等","output":23.12},{"planet":"HP-64T 三","richness":"中等","output":22.64},{"planet":"L-B55M 七","richness":"中等","output":22.11},{"planet":"JA-O6J 七","richness":"贫瘠","output":19.07},{"planet":"V2-VC2 一","richness":"贫瘠","output":18.75},{"planet":"CX65-5 四","richness":"贫瘠","output":17.68},{"planet":"JA-O6J 十一","richness":"贫瘠","output":17.35}]},"凝缩液":{"max_output":25.05,"count":6,"records":[{"planet":"SNFV-I 三","richness":"完美","output":25.05},{"planet":"8B-2YA 七","richness":"完美","output":24.64},{"planet":"JA-O6J 二","richness":"富裕","output":19.54},{"planet":"V2-VC2 二","richness":"富裕","output":17.78},{"planet":"L-B55M 九","richness":"富裕","output":17.72},{"planet":"JA-O6J 十二","richness":"中等","output":17.39}]},"浓缩合金":{"max_output":32.52,"count":4,"records":[{"planet":"SNFV-I 八","richness":"完美","output":32.52},{"planet":"8B-2YA 六","richness":"富裕","output":28.46},{"planet":"8B-2YA 三","richness":"中等","output":24.86},{"planet":"CX65-5 三","richness":"贫瘠","output":18.6}]},"透光复合物":{"max_output":30.81,"count":4,"records":[{"planet":"L-B55M 三","richness":"富裕","output":30.81},{"planet":"SNFV-I 五","richness":"富裕","output":28.6},{"planet":"8B-2YA 四","richness":"富裕","output":26.48},{"planet":"JA-O6J 三","richness":"中等","output":22.43}]},"贵金属":{"max_output":35.72,"count":7,"records":[{"planet":"SNFV-I 三","richness":"完美","output":35.72},{"planet":"8B-2YA 三","richness":"完美","output":32.9},{"planet":"8B-2YA 六","richness":"富裕","output":28.72},{"planet":"V2-VC2 三","richness":"富裕","output":27.74},{"planet":"SNFV-I 八","richness":"富裕","output":26.62},{"planet":"CX65-5 三","richness":"富裕","output":26.4},{"planet":"SNFV-I 十一","richness":"中等","output":25.22}]},"多样复合物":{"max_output":33.37,"count":3,"records":[{"planet":"JA-O6J 六","richness":"完美","output":33.37},{"planet":"SNFV-I 十一","richness":"中等","output":23.0},{"planet":"SNFV-I 十三","richness":"中等","output":19.6}]},"建筑模块":{"max_output":25.14,"count":11,"records":[{"planet":"JA-O6J 十","richness":"中等","output":25.14},{"planet":"SNFV-I 二","richness":"中等","output":22.5},{"planet":"8B-2YA 一","richness":"中等","output":21.9},{"planet":"SNFV-I 七","richness":"中等","output":21.42},{"planet":"SNFV-I 六","richness":"中等","output":20.9},{"planet":"HP-64T 一","richness":"中等","output":20.6},{"planet":"V2-VC2 三","richness":"贫瘠","output":19.61},{"planet":"8B-2YA 八","richness":"贫瘠","output":17.76},{"planet":"L-B55M 一","richness":"贫瘠","output":16.32},{"planet":"CX65-5 一","richness":"贫瘠","output":15.92},{"planet":"8B-2YA 二","richness":"贫瘠","output":14.42}]},"重金属":{"max_output":27.15,"count":1,"records":[{"planet":"JA-O6J 十二","richness":"富裕","output":27.15}]},"反应金属":{"max_output":8.71,"count":14,"records":[{"planet":"JA-O6J 十一","richness":"富裕","output":8.71},{"planet":"SNFV-I 十二","richness":"完美","output":8.53},{"planet":"L-B55M 四","richness":"富裕","output":8.1},{"planet":"L-B55M 三","richness":"富裕","output":7.91},{"planet":"8B-2YA 四","richness":"富裕","output":7.83},{"planet":"L-B55M 二","richness":"富裕","output":7.36},{"planet":"JA-O6J 三","richness":"富裕","output":7.3},{"planet":"L-B55M 六","richness":"中等","output":6.9},{"planet":"SNFV-I 七","richness":"中等","output":6.43},{"planet":"HP-64T 四","richness":"中等","output":6.39},{"planet":"HP-64T 二","richness":"中等","output":6.37},{"planet":"JA-O6J 四","richness":"中等","output":6.22},{"planet":"JA-O6J 十","richness":"中等","output":5.78},{"planet":"SNFV-I 五","richness":"贫瘠","output":4.28}]},"冷却剂":{"max_output":21.05,"count":9,"records":[{"planet":"HP-64T 三","richness":"富裕","output":21.05},{"planet":"CX65-5 三","richness":"富裕","output":20.79},{"planet":"SNFV-I 十二","richness":"富裕","output":19.77},{"planet":"SNFV-I 十三","richness":"富裕","output":18.77},{"planet":"L-B55M 七","richness":"中等","output":16.46},{"planet":"JA-O6J 六","richness":"中等","output":13.5},{"planet":"CX65-5 七","richness":"贫瘠","output":12.45},{"planet":"JA-O6J 九","richness":"贫瘠","output":12.24},{"planet":"JA-O6J 十一","richness":"贫瘠","output":12.14}]},"光泽合金":{"max_output":31.76,"count":12,"records":[{"planet":"SNFV-I 九","richness":"富裕","output":31.76},{"planet":"L-B55M 六","richness":"富裕","output":29.76},{"planet":"V2-VC2 二","richness":"富裕","output":26.8},{"planet":"JA-O6J 八","richness":"中等","output":26.57},{"planet":"CX65-5 七","richness":"富裕","output":25.5},{"planet":"CX65-5 四","richness":"中等","output":21.48},{"planet":"JA-O6J 五","richness":"贫瘠","output":19.05},{"planet":"JA-O6J 一","richness":"贫瘠","output":18.8},{"planet":"L-B55M 五","richness":"贫瘠","output":17.89},{"planet":"CX65-5 九","richness":"贫瘠","output":16.8},{"planet":"CX65-5 一","richness":"贫瘠","output":14.84},{"planet":"SNFV-I 一","richness":"贫瘠","output":14.44}]},"工业纤维":{"max_output":9.73,"count":7,"records":[{"planet":"SNFV-I 三","richness":"完美","output":9.73},{"planet":"8B-2YA 七","richness":"富裕","output":6.79},{"planet":"8B-2YA 三","richness":"中等","output":6.17},{"planet":"HP-64T 五","richness":"中等","output":5.65},{"planet":"L-B55M 一","richness":"中等","output":5.54},{"planet":"8B-2YA 五","richness":"贫瘠","output":4.91},{"planet":"CX65-5 十","richness":"贫瘠","output":4.07}]},"灵巧单元建筑模块":{"max_output":18.04,"count":1,"records":[{"planet":"SNFV-I 十","richness":"富裕","output":18.04}]},"光滑复合物":{"max_output":32.92,"count":8,"records":[{"planet":"HP-64T 四","richness":"完美","output":32.92},{"planet":"CX65-5 四","richness":"完美","output":32.82},{"planet":"JA-O6J 九","richness":"富裕","output":28.43},{"planet":"V2-VC2 一","richness":"中等","output":21.86},{"planet":"SNFV-I 十二","richness":"中等","output":21.78},{"planet":"CX65-5 九","richness":"中等","output":21.34},{"planet":"CX65-5 六","richness":"中等","output":20.32},{"planet":"JA-O6J 八","richness":"贫瘠","output":19.26}]},"杂色复合物":{"max_output":20.48,"count":2,"records":[{"planet":"V2-VC2 二","richness":"中等","output":20.48},{"planet":"CX65-5 二","richness":"贫瘠","output":18.2}]},"悬浮等离子":{"max_output":117.03,"count":5,"records":[{"planet":"JA-O6J 二","richness":"富裕","output":117.03},{"planet":"L-B55M 四","richness":"中等","output":88.0},{"planet":"SNFV-I 七","richness":"中等","output":83.16},{"planet":"L-B55M 二","richness":"中等","output":81.57},{"planet":"JA-O6J 十","richness":"中等","output":81.12}]},"黑暗复合物":{"max_output":19.99,"count":4,"records":[{"planet":"L-B55M 五","richness":"中等","output":19.99},{"planet":"SNFV-I 四","richness":"贫瘠","output":16.1},{"planet":"8B-2YA 八","richness":"贫瘠","output":12.8},{"planet":"HP-64T 一","richness":"贫瘠","output":12.68}]},"离子溶液":{"max_output":13.16,"count":8,"records":[{"planet":"JA-O6J 七","richness":"富裕","output":13.16},{"planet":"CX65-5 九","richness":"完美","output":12.89},{"planet":"JA-O6J 六","richness":"富裕","output":12.21},{"planet":"JA-O6J 五","richness":"富裕","output":11.73},{"planet":"CX65-5 五","richness":"中等","output":9.85},{"planet":"CX65-5 六","richness":"中等","output":8.56},{"planet":"HP-64T 四","richness":"中等","output":7.89},{"planet":"CX65-5 八","richness":"中等","output":7.66}]},"闪光合金":{"max_output":27.26,"count":7,"records":[{"planet":"L-B55M 四","richness":"富裕","output":27.26},{"planet":"CX65-5 二","richness":"富裕","output":26.56},{"planet":"JA-O6J 四","richness":"中等","output":21.92},{"planet":"V2-VC2 三","richness":"中等","output":21.61},{"planet":"SNFV-I 七","richness":"中等","output":21.3},{"planet":"HP-64T 二","richness":"中等","output":20.94},{"planet":"8B-2YA 四","richness":"中等","output":18.92}]},"纤维复合物":{"max_output":36.7,"count":9,"records":[{"planet":"SNFV-I 八","richness":"完美","output":36.7},{"planet":"CX65-5 五","richness":"完美","output":32.96},{"planet":"V2-VC2 一","richness":"富裕","output":27.97},{"planet":"SNFV-I 十","richness":"富裕","output":27.04},{"planet":"L-B55M 七","richness":"中等","output":22.6},{"planet":"8B-2YA 三","richness":"中等","output":22.54},{"planet":"HP-64T 三","richness":"中等","output":20.68},{"planet":"CX65-5 七","richness":"中等","output":20.66},{"planet":"JA-O6J 十一","richness":"贫瘠","output":19.59}]},"液化臭氧":{"max_output":45.3,"count":10,"records":[{"planet":"SNFV-I 十","richness":"完美","output":45.3},{"planet":"SNFV-I 十一","richness":"完美","output":41.77},{"planet":"SNFV-I 十三","richness":"完美","output":41.55},{"planet":"SNFV-I 三","richness":"富裕","output":36.48},{"planet":"8B-2YA 六","richness":"富裕","output":35.5},{"planet":"8B-2YA 三","richness":"富裕","output":34.6},{"planet":"SNFV-I 八","richness":"富裕","output":33.25},{"planet":"JA-O6J 六","richness":"中等","output":31.24},{"planet":"CX65-5 三","richness":"中等","output":25.63},{"planet":"8B-2YA 七","richness":"中等","output":23.95}]},"等离子体团":{"max_output":1.46,"count":9,"records":[{"planet":"HP-64T 六","richness":"中等","output":1.46},{"planet":"JA-O6J 二","richness":"中等","output":1.45},{"planet":"SNFV-I 一","richness":"中等","output":1.3},{"planet":"SNFV-I 二","richness":"中等","output":1.28},{"planet":"8B-2YA 二","richness":"中等","output":1.2},{"planet":"CX65-5 十","richness":"中等","output":1.18},{"planet":"L-B55M 五","richness":"贫瘠","output":1.12},{"planet":"L-B55M 八","richness":"贫瘠","output":1.08},{"planet":"8B-2YA 五","richness":"贫瘠","output":1.07}]},"重水":{"max_output":316.8,"count":3,"records":[{"planet":"SNFV-I 十","richness":"富裕","output":316.8},{"planet":"SNFV-I 十三","richness":"中等","output":251.2},{"planet":"8B-2YA 七","richness":"中等","output":217.2}]},"基础金属":{"max_output":10.01,"count":15,"records":[{"planet":"SNFV-I 十","richness":"完美","output":10.01},{"planet":"CX65-5 八","richness":"完美","output":8.56},{"planet":"SNFV-I 八","richness":"完美","output":8.44},{"planet":"JA-O6J 五","richness":"富裕","output":8.13},{"planet":"CX65-5 五","richness":"富裕","output":7.83},{"planet":"L-B55M 七","richness":"富裕","output":7.5},{"planet":"L-B55M 六","richness":"富裕","output":7.42},{"planet":"HP-64T 三","richness":"富裕","output":7.39},{"planet":"L-B55M 八","richness":"中等","output":6.45},{"planet":"SNFV-I 三","richness":"中等","output":6.41},{"planet":"8B-2YA 一","richness":"中等","output":5.87},{"planet":"CX65-5 一","richness":"中等","output":5.85},{"planet":"L-B55M 九","richness":"贫瘠","output":4.69},{"planet":"8B-2YA 五","richness":"贫瘠","output":4.61},{"planet":"SNFV-I 四","richness":"贫瘠","output":3.64}]},"同位素燃料":{"max_output":3.33,"count":4,"records":[{"planet":"JA-O6J 四","richness":"中等","output":3.33},{"planet":"SNFV-I 六","richness":"中等","output":3.13},{"planet":"JA-O6J 一","richness":"贫瘠","output":2.85},{"planet":"HP-64T 一","richness":"贫瘠","output":1.9}]},"聚芳酰胺":{"max_output":22.51,"count":12,"records":[{"planet":"JA-O6J 七","richness":"完美","output":22.51},{"planet":"SNFV-I 十三","richness":"完美","output":21.53},{"planet":"JA-O6J 八","richness":"富裕","output":20.76},{"planet":"CX65-5 二","richness":"富裕","output":20.63},{"planet":"CX65-5 六","richness":"富裕","output":19.76},{"planet":"JA-O6J 九","richness":"富裕","output":19.01},{"planet":"8B-2YA 六","richness":"富裕","output":18.97},{"planet":"V2-VC2 一","richness":"富裕","output":18.19},{"planet":"SNFV-I 九","richness":"富裕","output":17.84},{"planet":"JA-O6J 十一","richness":"中等","output":16.93},{"planet":"SNFV-I 十一","richness":"贫瘠","output":12.13},{"planet":"CX65-5 八","richness":"贫瘠","output":12.09}]}}}