{"region":"非塔波利斯","constellation":"3-U491","materials":{"硅结构铸材":{"max_output":21.08,"count":8,"records":[{"planet":"5-LCI7 六","richness":"完美","output":21.08},{"planet":"2-F3OE 四","richness":"富裕","output":16.39},{"planet":"TR07-S 四","richness":"中等","output":13.57},{"planet":"Y2-I3W 二","richness":"中等","output":13.41},{"planet":"Y2-I3W 四","richness":"贫瘠","output":9.86},{"planet":"VNGJ-U 九","richness":"贫瘠","output":9.8},{"planet":"5-LCI7 四","richness":"贫瘠","output":8.92},{"planet":"CL-J9W 七","richness":"贫瘠","output":7.85}]},"有毒金属":{"max_output":10.66,"count":12,"records":[{"planet":"2-F3OE 七","richness":"完美","output":10.66},{"planet":"AZN-D2 二","richness":"完美","output":10.49},{"planet":"VNGJ-U 五","richness":"富裕","output":8.0},{"planet":"E-PR0S 三","richness":"中等","output":7.34},{"planet":"VVO-R6 三","richness":"中等","output":6.74},{"planet":"TR07-S 二","richness":"中等","output":6.67},{"planet":"AZN-D2 九","richness":"中等","output":6.47},{"planet":"VNGJ-U 二","richness":"贫瘠","output":5.89},{"planet":"2-F3OE 一","richness":"贫瘠","output":5.87},{"planet":"5-LCI7 一","richness":"贫瘠","output":5.76},{"planet":"AZN-D2 一","richness":"贫瘠","output":5.52},{"planet":"E-PR0S 二","richness":"贫瘠","output":4.55}]},"稀有气体":{"max_output":39.58,"count":10,"records":[{"planet":"2-F3OE 十","richness":"富裕","output":39.58},{"planet":"VNGJ-U 三","richness":"完美","output":39.5},{"planet":"E-PR0S 六","richness":"富裕","output":36.9},{"planet":"5-LCI7 十三","richness":"富裕","output":34.7},{"planet":"AZN-D2 四","richness":"富裕","output":32.25},{"planet":"TR07-S 六","richness":"中等","output":28.7},{"planet":"2-F3OE 九","richness":"中等","output":28.25},{"planet":"TR07-S 三","richness":"中等","output":24.83},{"planet":"E-PR0S 七","richness":"贫瘠","output":22.77},{"planet":"5-LCI7 十二","richness":"贫瘠","output":21.65}]},"晶体复合物":{"max_output":40.65,"count":7,"records":[{"planet":"2-F3OE 六","richness":"完美","output":40.65},{"planet":"VVO-R6 四","richness":"富裕","output":34.82},{"planet":"AZN-D2 二","richness":"富裕","output":31.85},{"planet":"E-PR0S 五","richness":"中等","output":29.82},{"planet":"5-LCI7 六","richness":"中等","output":25.3},{"planet":"TR07-S 一","richness":"中等","output":24.6},{"planet":"2-F3OE 七","richness":"贫瘠","output":20.63}]},"精密合金":{"max_output":37.08,"count":12,"records":[{"planet":"E-PR0S 八","richness":"富裕","output":37.08},{"planet":"TR07-S 七","richness":"中等","output":31.88},{"planet":"E-PR0S 二","richness":"中等","output":29.63},{"planet":"2-F3OE 八","richness":"中等","output":27.6},{"planet":"AZN-D2 九","richness":"中等","output":25.63},{"planet":"2-F3OE 三","richness":"贫瘠","output":23.4},{"planet":"5-LCI7 三","richness":"贫瘠","output":20.06},{"planet":"VVO-R6 一","richness":"贫瘠","output":19.71},{"planet":"2-F3OE 一","richness":"贫瘠","output":19.18},{"planet":"CL-J9W 六","richness":"贫瘠","output":18.93},{"planet":"TR07-S 二","richness":"贫瘠","output":17.76},{"planet":"AZN-D2 一","richness":"贫瘠","output":15.6}]},"浓缩合金":{"max_output":46.23,"count":4,"records":[{"planet":"E-PR0S 四","richness":"完美","output":46.23},{"planet":"VNGJ-U 七","richness":"富裕","output":37.01},{"planet":"5-LCI7 十","richness":"富裕","output":31.73},{"planet":"2-F3OE 五","richness":"中等","output":26.52}]},"多样复合物":{"max_output":46.8,"count":7,"records":[{"planet":"E-PR0S 四","richness":"完美","output":46.8},{"planet":"2-F3OE 五","richness":"完美","output":45.83},{"planet":"VNGJ-U 五","richness":"富裕","output":31.39},{"planet":"2-F3OE 四","richness":"中等","output":28.8},{"planet":"VVO-R6 二","richness":"中等","output":27.76},{"planet":"VNGJ-U 七","richness":"中等","output":27.74},{"planet":"Y2-I3W 五","richness":"中等","output":25.74}]},"灵巧单元建筑模块":{"max_output":30.87,"count":7,"records":[{"planet":"E-PR0S 四","richness":"完美","output":30.87},{"planet":"2-F3OE 二","richness":"富裕","output":26.2},{"planet":"Y2-I3W 五","richness":"中等","output":19.37},{"planet":"VVO-R6 二","richness":"中等","output":16.36},{"planet":"5-LCI7 二","richness":"中等","output":15.62},{"planet":"E-PR0S 一","richness":"贫瘠","output":14.9},{"planet":"5-LCI7 七","richness":"贫瘠","output":14.67}]},"透光复合物":{"max_output":40.95,"count":5,"records":[{"planet":"2-F3OE 六","richness":"完美","output":40.95},{"planet":"E-PR0S 五","richness":"富裕","output":37.58},{"planet":"VVO-R6 四","richness":"富裕","output":31.6},{"planet":"5-LCI7 五","richness":"中等","output":23.9},{"planet":"Y2-I3W 七","richness":"中等","output":23.44}]},"光彩合金":{"max_output":40.48,"count":10,"records":[{"planet":"AZN-D2 五","richness":"完美","output":40.48},{"planet":"TR07-S 五","richness":"富裕","output":39.18},{"planet":"E-PR0S 六","richness":"富裕","output":38.33},{"planet":"CL-J9W 四","richness":"完美","output":37.28},{"planet":"5-LCI7 九","richness":"富裕","output":34.39},{"planet":"VVO-R6 五","richness":"富裕","output":31.97},{"planet":"CL-J9W 三","richness":"富裕","output":31.74},{"planet":"AZN-D2 七","richness":"中等","output":28.75},{"planet":"AZN-D2 三","richness":"中等","output":27.7},{"planet":"Y2-I3W 十","richness":"中等","output":22.82}]},"活性气体":{"max_output":39.41,"count":27,"records":[{"planet":"5-LCI7 十","richness":"完美","output":39.41},{"planet":"2-F3OE 七","richness":"富裕","output":38.13},{"planet":"5-LCI7 五","richness":"富裕","output":36.55},{"planet":"E-PR0S 四","richness":"富裕","output":36.02},{"planet":"TR07-S 六","richness":"富裕","output":35.8},{"planet":"5-LCI7 九","richness":"富裕","output":35.02},{"planet":"VVO-R6 三","richness":"富裕","output":33.46},{"planet":"TR07-S 五","richness":"富裕","output":33.25},{"planet":"E-PR0S 五","richness":"富裕","output":32.9},{"planet":"CL-J9W 四","richness":"富裕","output":32.89},{"planet":"VNGJ-U 七","richness":"富裕","output":32.83},{"planet":"Y2-I3W 十二","richness":"富裕","output":32.82},{"planet":"E-PR0S 七","richness":"富裕","output":32.05},{"planet":"AZN-D2 三","richness":"中等","output":29.8},{"planet":"5-LCI7 十一","richness":"中等","output":29.5},{"planet":"TR07-S 一","richness":"中等","output":28.5},{"planet":"VNGJ-U 六","richness":"中等","output":26.86},{"planet":"5-LCI7 十二","richness":"中等","output":26.52},{"planet":"VVO-R6 五","richness":"中等","output":26.43},{"planet":"2-F3OE 十","richness":"中等","output":24.8}]},"建筑模块":{"max_output":34.38,"count":12,"records":[{"planet":"Y2-I3W 七","richness":"富裕","output":34.38},{"planet":"TR07-S 一","richness":"中等","output":32.58},{"planet":"2-F3OE 六","richness":"中等","output":27.95},{"planet":"E-PR0S 三","richness":"中等","output":27.0},{"planet":"AZN-D2 二","richness":"中等","output":25.85},{"planet":"2-F3OE 一","richness":"中等","output":24.6},{"planet":"AZN-D2 一","richness":"贫瘠","output":23.27},{"planet":"VNGJ-U 一","richness":"贫瘠","output":21.19},{"planet":"VVO-R6 四","richness":"贫瘠","output":21.0},{"planet":"Y2-I3W 十二","richness":"贫瘠","output":20.84},{"planet":"CL-J9W 二","richness":"贫瘠","output":17.5},{"planet":"VVO-R6 一","richness":"贫瘠","output":16.88}]},"重金属":{"max_output":36.08,"count":2,"records":[{"planet":"2-F3OE 二","richness":"富裕","output":36.08},{"planet":"Y2-I3W 十一","richness":"贫瘠","output":17.5}]},"凝缩液":{"max_output":29.23,"count":8,"records":[{"planet":"5-LCI7 八","richness":"完美","output":29.23},{"planet":"5-LCI7 十","richness":"完美","output":27.17},{"planet":"CL-J9W 五","richness":"富裕","output":21.54},{"planet":"5-LCI7 七","richness":"中等","output":19.15},{"planet":"Y2-I3W 六","richness":"中等","output":17.13},{"planet":"Y2-I3W 十一","richness":"中等","output":16.7},{"planet":"Y2-I3W 五","richness":"中等","output":15.92},{"planet":"CL-J9W 六","richness":"中等","output":15.5}]},"冷却剂":{"max_output":27.72,"count":13,"records":[{"planet":"2-F3OE 四","richness":"完美","output":27.72},{"planet":"TR07-S 三","richness":"富裕","output":26.45},{"planet":"5-LCI7 十一","richness":"完美","output":26.35},{"planet":"E-PR0S 七","richness":"富裕","output":25.83},{"planet":"5-LCI7 六","richness":"富裕","output":24.56},{"planet":"TR07-S 六","richness":"中等","output":21.7},{"planet":"E-PR0S 六","richness":"中等","output":20.85},{"planet":"AZN-D2 六","richness":"中等","output":20.47},{"planet":"AZN-D2 四","richness":"中等","output":18.63},{"planet":"2-F3OE 九","richness":"中等","output":17.7},{"planet":"5-LCI7 十二","richness":"中等","output":17.47},{"planet":"CL-J9W 五","richness":"中等","output":15.0},{"planet":"CL-J9W 六","richness":"中等","output":14.67}]},"反应金属":{"max_output":10.81,"count":23,"records":[{"planet":"E-PR0S 六","richness":"完美","output":10.81},{"planet":"AZN-D2 四","richness":"完美","output":10.61},{"planet":"5-LCI7 十一","richness":"完美","output":10.32},{"planet":"5-LCI7 九","richness":"完美","output":10.23},{"planet":"VNGJ-U 八","richness":"完美","output":10.19},{"planet":"TR07-S 五","richness":"富裕","output":10.07},{"planet":"AZN-D2 八","richness":"富裕","output":9.89},{"planet":"AZN-D2 七","richness":"富裕","output":9.64},{"planet":"Y2-I3W 十","richness":"富裕","output":9.47},{"planet":"VVO-R6 四","richness":"富裕","output":9.31},{"planet":"Y2-I3W 十二","richness":"富裕","output":8.82},{"planet":"5-LCI7 十三","richness":"富裕","output":8.52},{"planet":"VNGJ-U 六","richness":"富裕","output":8.49},{"planet":"2-F3OE 六","richness":"富裕","output":8.46},{"planet":"VNGJ-U 二","richness":"富裕","output":8.16},{"planet":"5-LCI7 五","richness":"中等","output":7.81},{"planet":"Y2-I3W 八","richness":"中等","output":7.1},{"planet":"AZN-D2 五","richness":"中等","output":6.99},{"planet":"AZN-D2 六","richness":"中等","output":6.91},{"planet":"TR07-S 六","richness":"中等","output":6.76}]},"杂色复合物":{"max_output":34.7,"count":4,"records":[{"planet":"VNGJ-U 一","richness":"富裕","output":34.7},{"planet":"TR07-S 七","richness":"中等","output":29.25},{"planet":"CL-J9W 五","richness":"中等","output":28.24},{"planet":"E-PR0S 一","richness":"中等","output":26.0}]},"光泽合金":{"max_output":40.55,"count":23,"records":[{"planet":"AZN-D2 三","richness":"完美","output":40.55},{"planet":"TR07-S 五","richness":"富裕","output":38.71},{"planet":"5-LCI7 九","richness":"富裕","output":37.06},{"planet":"AZN-D2 五","richness":"富裕","output":37.05},{"planet":"Y2-I3W 十一","richness":"富裕","output":33.46},{"planet":"E-PR0S 七","richness":"富裕","output":32.98},{"planet":"E-PR0S 八","richness":"富裕","output":32.75},{"planet":"VNGJ-U 六","richness":"富裕","output":32.18},{"planet":"CL-J9W 六","richness":"富裕","output":31.88},{"planet":"5-LCI7 十一","richness":"富裕","output":31.44},{"planet":"E-PR0S 六","richness":"中等","output":30.45},{"planet":"2-F3OE 八","richness":"中等","output":29.65},{"planet":"AZN-D2 七","richness":"中等","output":29.4},{"planet":"E-PR0S 三","richness":"中等","output":26.4},{"planet":"2-F3OE 十","richness":"中等","output":26.18},{"planet":"CL-J9W 七","richness":"中等","output":25.83},{"planet":"5-LCI7 十三","richness":"中等","output":25.73},{"planet":"5-LCI7 十二","richness":"中等","output":25.54},{"planet":"AZN-D2 四","richness":"贫瘠","output":22.63},{"planet":"AZN-D2 六","richness":"贫瘠","output":22.35}]},"纳米体":{"max_output":8.03,"count":2,"records":[{"planet":"VNGJ-U 四","richness":"富裕","output":8.03},{"planet":"Y2-I3W 十二","richness":"中等","output":6.91}]},"超张力塑料":{"max_output":19.92,"count":18,"records":[{"planet":"2-F3OE 六","richness":"中等","output":19.92},{"planet":"VNGJ-U 二","richness":"中等","output":19.46},{"planet":"VNGJ-U 九","richness":"中等","output":18.82},{"planet":"TR07-S 七","richness":"中等","output":18.74},{"planet":"Y2-I3W 三","richness":"中等","output":18.61},{"planet":"5-LCI7 四","richness":"中等","output":18.56},{"planet":"VVO-R6 一","richness":"中等","output":18.32},{"planet":"Y2-I3W 二","richness":"中等","output":17.97},{"planet":"AZN-D2 二","richness":"中等","output":17.37},{"planet":"E-PR0S 二","richness":"中等","output":16.92},{"planet":"5-LCI7 一","richness":"中等","output":16.91},{"planet":"CL-J9W 二","richness":"中等","output":16.48},{"planet":"5-LCI7 三","richness":"中等","output":15.89},{"planet":"TR07-S 四","richness":"贫瘠","output":13.76},{"planet":"CL-J9W 一","richness":"贫瘠","output":12.97},{"planet":"E-PR0S 八","richness":"贫瘠","output":12.72},{"planet":"CL-J9W 七","richness":"贫瘠","output":11.25},{"planet":"Y2-I3W 四","richness":"贫瘠","output":9.61}]},"黑暗复合物":{"max_output":28.9,"count":13,"records":[{"planet":"5-LCI7 三","richness":"中等","output":28.9},{"planet":"E-PR0S 二","richness":"中等","output":26.93},{"planet":"5-LCI7 一","richness":"中等","output":25.63},{"planet":"2-F3OE 八","richness":"中等","output":24.82},{"planet":"TR07-S 二","richness":"贫瘠","output":23.89},{"planet":"AZN-D2 九","richness":"贫瘠","output":23.02},{"planet":"TR07-S 四","richness":"贫瘠","output":22.13},{"planet":"2-F3OE 一","richness":"贫瘠","output":22.1},{"planet":"2-F3OE 三","richness":"贫瘠","output":21.35},{"planet":"AZN-D2 一","richness":"贫瘠","output":19.88},{"planet":"5-LCI7 四","richness":"贫瘠","output":19.42},{"planet":"E-PR0S 三","richness":"贫瘠","output":16.4},{"planet":"VNGJ-U 九","richness":"贫瘠","output":15.79}]},"贵金属":{"max_output":32.87,"count":4,"records":[{"planet":"Y2-I3W 六","richness":"富裕","output":32.87},{"planet":"5-LCI7 八","richness":"富裕","output":31.42},{"planet":"5-LCI7 六","richness":"中等","output":28.32},{"planet":"5-LCI7 二","richness":"贫瘠","output":19.82}]},"光滑复合物":{"max_output":40.5,"count":14,"records":[{"planet":"AZN-D2 五","richness":"完美","output":40.5},{"planet":"AZN-D2 三","richness":"富裕","output":37.9},{"planet":"TR07-S 三","richness":"富裕","output":35.36},{"planet":"AZN-D2 四","richness":"富裕","output":33.35},{"planet":"AZN-D2 八","richness":"富裕","output":33.02},{"planet":"2-F3OE 九","richness":"中等","output":29.93},{"planet":"CL-J9W 四","richness":"中等","output":27.65},{"planet":"Y2-I3W 九","richness":"中等","output":27.51},{"planet":"2-F3OE 二","richness":"中等","output":26.43},{"planet":"AZN-D2 六","richness":"中等","output":25.82},{"planet":"E-PR0S 一","richness":"贫瘠","output":23.35},{"planet":"CL-J9W 三","richness":"贫瘠","output":20.65},{"planet":"Y2-I3W 一","richness":"贫瘠","output":20.54},{"planet":"VNGJ-U 八","richness":"贫瘠","output":19.94}]},"闪光合金":{"max_output":38.13,"count":8,"records":[{"planet":"AZN-D2 二","richness":"富裕","output":38.13},{"planet":"5-LCI7 五","richness":"富裕","output":31.73},{"planet":"5-LCI7 二","richness":"富裕","output":30.96},{"planet":"VNGJ-U 三","richness":"富裕","output":30.94},{"planet":"VNGJ-U 四","richness":"中等","output":26.59},{"planet":"E-PR0S 五","richness":"贫瘠","output":23.02},{"planet":"Y2-I3W 一","richness":"中等","output":22.91},{"planet":"VNGJ-U 一","richness":"贫瘠","output":21.29}]},"悬浮等离子":{"max_output":140.04,"count":7,"records":[{"planet":"E-PR0S 五","richness":"富裕","output":140.04},{"planet":"Y2-I3W 七","richness":"中等","output":101.93},{"planet":"VVO-R6 三","richness":"中等","output":96.05},{"planet":"TR07-S 一","richness":"中等","output":94.72},{"planet":"2-F3OE 七","richness":"贫瘠","output":82.62},{"planet":"E-PR0S 八","richness":"贫瘠","output":80.73},{"planet":"Y2-I3W 十一","richness":"中等","output":78.66}]},"重水":{"max_output":454.0,"count":4,"records":[{"planet":"2-F3OE 五","richness":"完美","output":454.0},{"planet":"Y2-I3W 五","richness":"完美","output":418.83},{"planet":"2-F3OE 四","richness":"富裕","output":377.25},{"planet":"E-PR0S 四","richness":"中等","output":261.0}]},"离子溶液":{"max_output":16.49,"count":17,"records":[{"planet":"AZN-D2 三","richness":"完美","output":16.49},{"planet":"2-F3OE 四","richness":"完美","output":16.33},{"planet":"AZN-D2 八","richness":"富裕","output":15.37},{"planet":"AZN-D2 七","richness":"富裕","output":14.73},{"planet":"TR07-S 三","richness":"富裕","output":14.56},{"planet":"5-LCI7 十一","richness":"富裕","output":13.5},{"planet":"5-LCI7 十三","richness":"富裕","output":13.37},{"planet":"VNGJ-U 五","richness":"富裕","output":12.62},{"planet":"Y2-I3W 八","richness":"富裕","output":12.61},{"planet":"AZN-D2 五","richness":"中等","output":11.29},{"planet":"5-LCI7 九","richness":"中等","output":10.48},{"planet":"CL-J9W 三","richness":"中等","output":10.42},{"planet":"Y2-I3W 十","richness":"中等","output":9.71},{"planet":"VVO-R6 五","richness":"中等","output":9.6},{"planet":"2-F3OE 十","richness":"贫瘠","output":8.76},{"planet":"2-F3OE 九","richness":"贫瘠","output":8.28},{"planet":"Y2-I3W 九","richness":"贫瘠","output":8.22}]},"同位素燃料":{"max_output":5.88,"count":13,"records":[{"planet":"2-F3OE 七","richness":"富裕","output":5.88},{"planet":"VNGJ-U 二","richness":"富裕","output":5.49},{"planet":"TR07-S 一","richness":"中等","output":4.77},{"planet":"VNGJ-U 四","richness":"中等","output":4.13},{"planet":"2-F3OE 一","richness":"中等","output":3.98},{"planet":"Y2-I3W 三","richness":"中等","output":3.97},{"planet":"2-F3OE 二","richness":"中等","output":3.72},{"planet":"2-F3OE 八","richness":"中等","output":3.61},{"planet":"AZN-D2 一","richness":"中等","output":3.55},{"planet":"2-F3OE 三","richness":"贫瘠","output":2.91},{"planet":"CL-J9W 一","richness":"贫瘠","output":2.79},{"planet":"VVO-R6 一","richness":"贫瘠","output":2.61},{"planet":"CL-J9W 二","richness":"贫瘠","output":2.14}]},"液化臭氧":{"max_output":55.23,"count":13,"records":[{"planet":"5-LCI7 十","richness":"完美","output":55.23},{"planet":"VVO-R6 二","richness":"完美","output":51.87},{"planet":"Y2-I3W 五","richness":"完美","output":49.68},{"planet":"2-F3OE 五","richness":"富裕","output":43.59},{"planet":"5-LCI7 七","richness":"富裕","output":42.84},{"planet":"E-PR0S 八","richness":"富裕","output":42.13},{"planet":"5-LCI7 八","richness":"富裕","output":40.17},{"planet":"E-PR0S 四","richness":"中等","output":38.28},{"planet":"Y2-I3W 六","richness":"中等","output":32.72},{"planet":"VNGJ-U 五","richness":"中等","output":32.13},{"planet":"5-LCI7 六","richness":"贫瘠","output":28.14},{"planet":"VNGJ-U 七","richness":"贫瘠","output":28.08},{"planet":"CL-J9W 五","richness":"贫瘠","output":23.0}]},"工业纤维":{"max_output":8.04,"count":8,"records":[{"planet":"5-LCI7 七","richness":"富裕","output":8.04},{"planet":"2-F3OE 五","richness":"中等","output":7.67},{"planet":"AZN-D2 九","richness":"中等","output":6.43},{"planet":"Y2-I3W 六","richness":"中等","output":6.37},{"planet":"TR07-S 七","richness":"贫瘠","output":6.19},{"planet":"2-F3OE 三","richness":"贫瘠","output":5.37},{"planet":"TR07-S 二","richness":"贫瘠","output":4.69},{"planet":"CL-J9W 一","richness":"贫瘠","output":4.65}]},"等离子体团":{"max_output":1.75,"count":10,"records":[{"planet":"VNGJ-U 三","richness":"中等","output":1.75},{"planet":"TR07-S 四","richness":"中等","output":1.7},{"planet":"Y2-I3W 二","richness":"中等","output":1.69},{"planet":"Y2-I3W 四","richness":"中等","output":1.67},{"planet":"Y2-I3W 三","richness":"中等","output":1.59},{"planet":"5-LCI7 三","richness":"中等","output":1.44},{"planet":"VNGJ-U 九","richness":"中等","output":1.4},{"planet":"E-PR0S 三","richness":"贫瘠","output":0.99},{"planet":"CL-J9W 一","richness":"贫瘠","output":0.99},{"planet":"5-LCI7 四","richness":"贫瘠","output":0.93}]},"纤维复合物":{"max_output":42.29,"count":15,"records":[{"planet":"5-LCI7 十","richness":"完美","output":42.29},{"planet":"VVO-R6 二","richness":"完美","output":42.23},{"planet":"TR07-S 三","richness":"富裕","output":40.95},{"planet":"AZN-D2 七","richness":"完美","output":40.02},{"planet":"AZN-D2 六","richness":"完美","output":39.8},{"planet":"Y2-I3W 六","richness":"完美","output":39.47},{"planet":"VNGJ-U 六","richness":"完美","output":38.52},{"planet":"Y2-I3W 八","richness":"富裕","output":35.49},{"planet":"TR07-S 六","richness":"富裕","output":33.31},{"planet":"AZN-D2 四","richness":"中等","output":27.68},{"planet":"AZN-D2 八","richness":"中等","output":26.52},{"planet":"CL-J9W 三","richness":"中等","output":26.36},{"planet":"5-LCI7 八","richness":"中等","output":24.29},{"planet":"VNGJ-U 七","richness":"中等","output":23.54},{"planet":"CL-J9W 四","richness":"中等","output":22.63}]},"基础金属":{"max_output":11.63,"count":27,"records":[{"planet":"5-LCI7 七","richness":"完美","output":11.63},{"planet":"2-F3OE 五","richness":"完美","output":11.19},{"planet":"2-F3OE 九","richness":"完美","output":10.84},{"planet":"AZN-D2 六","richness":"完美","output":10.78},{"planet":"E-PR0S 七","richness":"完美","output":10.51},{"planet":"TR07-S 五","richness":"富裕","output":10.37},{"planet":"2-F3OE 十","richness":"富裕","output":10.22},{"planet":"VNGJ-U 八","richness":"完美","output":10.17},{"planet":"VVO-R6 二","richness":"完美","output":10.08},{"planet":"TR07-S 七","richness":"富裕","output":9.73},{"planet":"AZN-D2 三","richness":"富裕","output":9.56},{"planet":"CL-J9W 四","richness":"富裕","output":8.25},{"planet":"5-LCI7 八","richness":"富裕","output":8.2},{"planet":"TR07-S 三","richness":"中等","output":7.88},{"planet":"TR07-S 四","richness":"中等","output":7.63},{"planet":"VVO-R6 五","richness":"中等","output":7.6},{"planet":"CL-J9W 七","richness":"中等","output":7.42},{"planet":"Y2-I3W 九","richness":"中等","output":7.4},{"planet":"Y2-I3W 十","richness":"中等","output":6.85},{"planet":"AZN-D2 九","richness":"中等","output":6.62}]},"聚芳酰胺":{"max_output":27.65,"count":18,"records":[{"planet":"TR07-S 六","richness":"完美","output":27.65},{"planet":"AZN-D2 七","richness":"完美","output":27.25},{"planet":"E-PR0S 一","richness":"完美","output":27.18},{"planet":"VNGJ-U 五","richness":"完美","output":27.02},{"planet":"TR07-S 五","richness":"富裕","output":26.55},{"planet":"2-F3OE 十","richness":"富裕","output":25.45},{"planet":"5-LCI7 十二","richness":"富裕","output":24.91},{"planet":"2-F3OE 九","richness":"中等","output":21.08},{"planet":"VVO-R6 五","richness":"富裕","output":20.82},{"planet":"Y2-I3W 八","richness":"富裕","output":20.5},{"planet":"AZN-D2 八","richness":"中等","output":19.95},{"planet":"2-F3OE 四","richness":"中等","output":18.68},{"planet":"Y2-I3W 一","richness":"中等","output":16.97},{"planet":"VNGJ-U 八","richness":"中等","output":16.56},{"planet":"E-PR0S 七","richness":"贫瘠","output":15.07},{"planet":"E-PR0S 六","richness":"贫瘠","output":13.97},{"planet":"VNGJ-U 六","richness":"贫瘠","output":13.49},{"planet":"Y2-I3W 九","richness":"贫瘠","output":13.25}]}}}