{"region":"血脉","constellation":"BI-NFW","materials":{"稀有气体":{"max_output":39.98,"count":13,"records":[{"planet":"5-P1Y2 十","richness":"完美","output":39.98},{"planet":"C-LBQS 十一","richness":"完美","output":36.85},{"planet":"C-LBQS 九","richness":"富裕","output":35.42},{"planet":"5-P1Y2 十三","richness":"富裕","output":34.73},{"planet":"C-LBQS 七","richness":"富裕","output":32.48},{"planet":"C-LBQS 十","richness":"富裕","output":32.31},{"planet":"KJ-QWL 六","richness":"富裕","output":29.74},{"planet":"J52-BH 三","richness":"中等","output":28.94},{"planet":"J52-BH 二","richness":"中等","output":27.7},{"planet":"KJ-QWL 一","richness":"中等","output":27.06},{"planet":"BWI1-9 五","richness":"中等","output":25.89},{"planet":"BWI1-9 七","richness":"中等","output":24.55},{"planet":"KJ-QWL 七","richness":"中等","output":24.53}]},"晶体复合物":{"max_output":35.5,"count":6,"records":[{"planet":"5-P1Y2 九","richness":"富裕","output":35.5},{"planet":"SVB-RE 三","richness":"富裕","output":30.16},{"planet":"SVB-RE 六","richness":"富裕","output":28.71},{"planet":"5-P1Y2 三","richness":"中等","output":23.98},{"planet":"KMQ4-V 六","richness":"中等","output":22.51},{"planet":"KMQ4-V 三","richness":"贫瘠","output":20.46}]},"硅结构铸材":{"max_output":16.52,"count":9,"records":[{"planet":"KMQ4-V 六","richness":"富裕","output":16.52},{"planet":"KMQ4-V 三","richness":"富裕","output":15.74},{"planet":"C-LBQS 五","richness":"中等","output":13.64},{"planet":"SVB-RE 一","richness":"中等","output":12.46},{"planet":"SVB-RE 五","richness":"中等","output":11.48},{"planet":"KJ-QWL 二","richness":"中等","output":10.37},{"planet":"C-LBQS 一","richness":"贫瘠","output":8.73},{"planet":"SVB-RE 四","richness":"贫瘠","output":8.69},{"planet":"KMQ4-V 一","richness":"贫瘠","output":8.05}]},"精密合金":{"max_output":32.78,"count":6,"records":[{"planet":"BWI1-9 八","richness":"富裕","output":32.78},{"planet":"C-LBQS 八","richness":"中等","output":25.97},{"planet":"SVB-RE 一","richness":"中等","output":25.64},{"planet":"KMQ4-V 一","richness":"中等","output":21.23},{"planet":"KJ-QWL 八","richness":"中等","output":21.21},{"planet":"SVB-RE 八","richness":"贫瘠","output":17.58}]},"浓缩合金":{"max_output":42.23,"count":12,"records":[{"planet":"5-P1Y2 十二","richness":"完美","output":42.23},{"planet":"C-LBQS 四","richness":"完美","output":39.56},{"planet":"C-LBQS 五","richness":"完美","output":39.03},{"planet":"SVB-RE 九","richness":"完美","output":36.96},{"planet":"5-P1Y2 五","richness":"富裕","output":35.23},{"planet":"KMQ4-V 五","richness":"富裕","output":28.23},{"planet":"5-P1Y2 六","richness":"中等","output":27.38},{"planet":"5-P1Y2 四","richness":"中等","output":26.15},{"planet":"KMQ4-V 六","richness":"中等","output":25.34},{"planet":"5-P1Y2 八","richness":"中等","output":24.82},{"planet":"5-P1Y2 十一","richness":"中等","output":24.15},{"planet":"C-LBQS 六","richness":"中等","output":22.7}]},"多样复合物":{"max_output":43.35,"count":5,"records":[{"planet":"5-P1Y2 六","richness":"完美","output":43.35},{"planet":"5-P1Y2 八","richness":"完美","output":41.88},{"planet":"5-P1Y2 十二","richness":"完美","output":41.5},{"planet":"5-P1Y2 十一","richness":"中等","output":29.13},{"planet":"KMQ4-V 三","richness":"中等","output":25.39}]},"活性气体":{"max_output":37.27,"count":18,"records":[{"planet":"5-P1Y2 十","richness":"富裕","output":37.27},{"planet":"C-LBQS 十","richness":"富裕","output":36.09},{"planet":"KJ-QWL 五","richness":"富裕","output":33.4},{"planet":"5-P1Y2 十三","richness":"富裕","output":32.5},{"planet":"5-P1Y2 五","richness":"富裕","output":32.33},{"planet":"5-P1Y2 四","richness":"中等","output":30.73},{"planet":"C-LBQS 十一","richness":"富裕","output":30.43},{"planet":"J52-BH 三","richness":"中等","output":27.5},{"planet":"BWI1-9 七","richness":"中等","output":26.73},{"planet":"SVB-RE 九","richness":"中等","output":25.93},{"planet":"KJ-QWL 六","richness":"中等","output":25.43},{"planet":"KMQ4-V 八","richness":"中等","output":25.32},{"planet":"C-LBQS 九","richness":"中等","output":24.31},{"planet":"5-P1Y2 九","richness":"贫瘠","output":21.35},{"planet":"J52-BH 二","richness":"贫瘠","output":20.66},{"planet":"KJ-QWL 七","richness":"贫瘠","output":20.61},{"planet":"C-LBQS 七","richness":"贫瘠","output":20.49},{"planet":"BWI1-9 五","richness":"贫瘠","output":18.57}]},"超张力塑料":{"max_output":25.15,"count":24,"records":[{"planet":"5-P1Y2 九","richness":"富裕","output":25.15},{"planet":"5-P1Y2 七","richness":"中等","output":20.17},{"planet":"5-P1Y2 二","richness":"中等","output":18.5},{"planet":"C-LBQS 三","richness":"中等","output":17.92},{"planet":"KMQ4-V 二","richness":"中等","output":17.42},{"planet":"BWI1-9 二","richness":"中等","output":17.37},{"planet":"BWI1-9 一","richness":"中等","output":17.23},{"planet":"C-LBQS 一","richness":"中等","output":16.94},{"planet":"SVB-RE 五","richness":"中等","output":16.88},{"planet":"SVB-RE 一","richness":"中等","output":16.73},{"planet":"5-P1Y2 三","richness":"中等","output":15.92},{"planet":"C-LBQS 二","richness":"贫瘠","output":14.05},{"planet":"KJ-QWL 四","richness":"贫瘠","output":13.76},{"planet":"BWI1-9 八","richness":"贫瘠","output":13.65},{"planet":"KJ-QWL 二","richness":"贫瘠","output":13.3},{"planet":"SVB-RE 八","richness":"中等","output":13.26},{"planet":"SVB-RE 二","richness":"贫瘠","output":13.05},{"planet":"KMQ4-V 七","richness":"贫瘠","output":12.61},{"planet":"KMQ4-V 一","richness":"贫瘠","output":12.33},{"planet":"C-LBQS 八","richness":"贫瘠","output":10.84}]},"有毒金属":{"max_output":7.72,"count":8,"records":[{"planet":"BWI1-9 四","richness":"富裕","output":7.72},{"planet":"5-P1Y2 十二","richness":"中等","output":7.47},{"planet":"C-LBQS 五","richness":"中等","output":7.35},{"planet":"KMQ4-V 五","richness":"中等","output":7.28},{"planet":"5-P1Y2 二","richness":"中等","output":7.13},{"planet":"SVB-RE 八","richness":"中等","output":6.47},{"planet":"SVB-RE 三","richness":"中等","output":5.53},{"planet":"KMQ4-V 二","richness":"贫瘠","output":3.94}]},"透光复合物":{"max_output":37.52,"count":1,"records":[{"planet":"5-P1Y2 九","richness":"富裕","output":37.52}]},"贵金属":{"max_output":42.92,"count":7,"records":[{"planet":"5-P1Y2 十一","richness":"完美","output":42.92},{"planet":"KMQ4-V 四","richness":"完美","output":38.79},{"planet":"5-P1Y2 一","richness":"富裕","output":37.75},{"planet":"C-LBQS 六","richness":"富裕","output":35.53},{"planet":"KMQ4-V 三","richness":"完美","output":35.35},{"planet":"5-P1Y2 八","richness":"富裕","output":33.35},{"planet":"5-P1Y2 五","richness":"中等","output":31.57}]},"重金属":{"max_output":33.92,"count":2,"records":[{"planet":"KJ-QWL 一","richness":"富裕","output":33.92},{"planet":"KJ-QWL 八","richness":"中等","output":26.03}]},"建筑模块":{"max_output":30.88,"count":8,"records":[{"planet":"5-P1Y2 三","richness":"中等","output":30.88},{"planet":"KJ-QWL 二","richness":"中等","output":26.09},{"planet":"SVB-RE 二","richness":"中等","output":24.51},{"planet":"KMQ4-V 二","richness":"中等","output":21.63},{"planet":"BWI1-9 三","richness":"贫瘠","output":20.26},{"planet":"C-LBQS 二","richness":"贫瘠","output":20.1},{"planet":"J52-BH 一","richness":"贫瘠","output":15.98},{"planet":"KJ-QWL 四","richness":"贫瘠","output":15.53}]},"灵巧单元建筑模块":{"max_output":25.1,"count":5,"records":[{"planet":"5-P1Y2 十一","richness":"富裕","output":25.1},{"planet":"5-P1Y2 六","richness":"富裕","output":24.85},{"planet":"SVB-RE 九","richness":"富裕","output":21.67},{"planet":"C-LBQS 六","richness":"中等","output":18.78},{"planet":"C-LBQS 四","richness":"中等","output":15.16}]},"凝缩液":{"max_output":27.05,"count":6,"records":[{"planet":"5-P1Y2 五","richness":"完美","output":27.05},{"planet":"J52-BH 四","richness":"富裕","output":20.72},{"planet":"J52-BH 五","richness":"中等","output":19.78},{"planet":"KJ-QWL 一","richness":"富裕","output":18.67},{"planet":"KJ-QWL 八","richness":"中等","output":16.43},{"planet":"BWI1-9 八","richness":"中等","output":15.93}]},"反应金属":{"max_output":10.55,"count":7,"records":[{"planet":"5-P1Y2 三","richness":"完美","output":10.55},{"planet":"BWI1-9 四","richness":"完美","output":9.32},{"planet":"BWI1-9 五","richness":"富裕","output":8.21},{"planet":"KJ-QWL 五","richness":"富裕","output":7.95},{"planet":"SVB-RE 三","richness":"富裕","output":7.16},{"planet":"SVB-RE 六","richness":"富裕","output":7.14},{"planet":"5-P1Y2 十三","richness":"贫瘠","output":5.82}]},"工业纤维":{"max_output":12.55,"count":18,"records":[{"planet":"5-P1Y2 十一","richness":"完美","output":12.55},{"planet":"KMQ4-V 四","richness":"完美","output":9.84},{"planet":"5-P1Y2 四","richness":"中等","output":7.34},{"planet":"C-LBQS 八","richness":"中等","output":7.05},{"planet":"BWI1-9 二","richness":"中等","output":6.92},{"planet":"5-P1Y2 八","richness":"中等","output":6.41},{"planet":"C-LBQS 三","richness":"中等","output":6.28},{"planet":"SVB-RE 九","richness":"中等","output":6.17},{"planet":"C-LBQS 四","richness":"中等","output":5.96},{"planet":"SVB-RE 七","richness":"中等","output":5.76},{"planet":"KMQ4-V 七","richness":"中等","output":5.69},{"planet":"SVB-RE 四","richness":"中等","output":5.57},{"planet":"5-P1Y2 七","richness":"贫瘠","output":4.86},{"planet":"BWI1-9 一","richness":"贫瘠","output":4.81},{"planet":"SVB-RE 二","richness":"贫瘠","output":4.72},{"planet":"KJ-QWL 四","richness":"贫瘠","output":4.65},{"planet":"SVB-RE 五","richness":"贫瘠","output":4.33},{"planet":"J52-BH 一","richness":"贫瘠","output":4.27}]},"冷却剂":{"max_output":25.43,"count":10,"records":[{"planet":"KMQ4-V 五","richness":"完美","output":25.43},{"planet":"5-P1Y2 十三","richness":"富裕","output":23.82},{"planet":"J52-BH 四","richness":"富裕","output":22.0},{"planet":"KMQ4-V 六","richness":"富裕","output":20.4},{"planet":"KJ-QWL 七","richness":"中等","output":16.6},{"planet":"C-LBQS 十","richness":"中等","output":14.9},{"planet":"C-LBQS 十一","richness":"中等","output":14.87},{"planet":"J52-BH 五","richness":"贫瘠","output":12.46},{"planet":"BWI1-9 五","richness":"贫瘠","output":12.39},{"planet":"BWI1-9 八","richness":"贫瘠","output":10.78}]},"纳米体":{"max_output":8.22,"count":3,"records":[{"planet":"SVB-RE 三","richness":"富裕","output":8.22},{"planet":"5-P1Y2 九","richness":"中等","output":7.43},{"planet":"BWI1-9 四","richness":"中等","output":6.02}]},"光彩合金":{"max_output":29.76,"count":3,"records":[{"planet":"J52-BH 三","richness":"中等","output":29.76},{"planet":"KMQ4-V 八","richness":"中等","output":26.09},{"planet":"KJ-QWL 六","richness":"中等","output":25.67}]},"光泽合金":{"max_output":35.46,"count":16,"records":[{"planet":"KMQ4-V 八","richness":"完美","output":35.46},{"planet":"5-P1Y2 十三","richness":"富裕","output":34.25},{"planet":"KJ-QWL 五","richness":"富裕","output":33.31},{"planet":"J52-BH 四","richness":"富裕","output":32.28},{"planet":"5-P1Y2 二","richness":"中等","output":30.27},{"planet":"C-LBQS 十一","richness":"中等","output":24.7},{"planet":"KJ-QWL 七","richness":"中等","output":24.27},{"planet":"KMQ4-V 二","richness":"中等","output":22.07},{"planet":"KJ-QWL 四","richness":"中等","output":21.69},{"planet":"BWI1-9 二","richness":"中等","output":21.32},{"planet":"J52-BH 五","richness":"贫瘠","output":21.02},{"planet":"C-LBQS 十","richness":"贫瘠","output":19.46},{"planet":"C-LBQS 二","richness":"贫瘠","output":18.33},{"planet":"KMQ4-V 七","richness":"贫瘠","output":16.41},{"planet":"KMQ4-V 一","richness":"贫瘠","output":14.54},{"planet":"SVB-RE 七","richness":"贫瘠","output":13.8}]},"光滑复合物":{"max_output":40.23,"count":10,"records":[{"planet":"5-P1Y2 一","richness":"完美","output":40.23},{"planet":"KJ-QWL 五","richness":"完美","output":36.1},{"planet":"5-P1Y2 十","richness":"富裕","output":32.35},{"planet":"C-LBQS 九","richness":"富裕","output":29.99},{"planet":"BWI1-9 五","richness":"富裕","output":29.81},{"planet":"C-LBQS 七","richness":"中等","output":26.8},{"planet":"C-LBQS 十","richness":"中等","output":26.47},{"planet":"BWI1-9 七","richness":"中等","output":23.65},{"planet":"KMQ4-V 八","richness":"中等","output":22.55},{"planet":"KJ-QWL 七","richness":"贫瘠","output":18.3}]},"黑暗复合物":{"max_output":27.32,"count":6,"records":[{"planet":"C-LBQS 三","richness":"中等","output":27.32},{"planet":"KJ-QWL 一","richness":"中等","output":24.13},{"planet":"5-P1Y2 二","richness":"贫瘠","output":19.68},{"planet":"SVB-RE 八","richness":"贫瘠","output":19.3},{"planet":"5-P1Y2 七","richness":"贫瘠","output":18.7},{"planet":"C-LBQS 八","richness":"贫瘠","output":15.13}]},"液化臭氧":{"max_output":59.44,"count":13,"records":[{"planet":"5-P1Y2 六","richness":"完美","output":59.44},{"planet":"5-P1Y2 五","richness":"完美","output":59.22},{"planet":"C-LBQS 四","richness":"完美","output":54.97},{"planet":"KMQ4-V 五","richness":"完美","output":46.17},{"planet":"KMQ4-V 六","richness":"完美","output":45.32},{"planet":"C-LBQS 五","richness":"富裕","output":45.25},{"planet":"5-P1Y2 十二","richness":"富裕","output":43.59},{"planet":"C-LBQS 六","richness":"富裕","output":41.74},{"planet":"5-P1Y2 四","richness":"富裕","output":39.72},{"planet":"J52-BH 五","richness":"中等","output":36.75},{"planet":"SVB-RE 九","richness":"中等","output":32.24},{"planet":"KMQ4-V 四","richness":"中等","output":28.77},{"planet":"KMQ4-V 三","richness":"中等","output":27.25}]},"离子溶液":{"max_output":15.6,"count":4,"records":[{"planet":"J52-BH 二","richness":"完美","output":15.6},{"planet":"C-LBQS 九","richness":"富裕","output":13.51},{"planet":"KJ-QWL 五","richness":"中等","output":9.63},{"planet":"5-P1Y2 十","richness":"贫瘠","output":8.58}]},"重水":{"max_output":423.0,"count":5,"records":[{"planet":"5-P1Y2 十二","richness":"完美","output":423.0},{"planet":"5-P1Y2 八","richness":"完美","output":412.75},{"planet":"5-P1Y2 四","richness":"富裕","output":368.25},{"planet":"5-P1Y2 十一","richness":"富裕","output":360.5},{"planet":"5-P1Y2 六","richness":"富裕","output":337.75}]},"纤维复合物":{"max_output":46.25,"count":14,"records":[{"planet":"5-P1Y2 八","richness":"完美","output":46.25},{"planet":"KMQ4-V 四","richness":"完美","output":40.37},{"planet":"5-P1Y2 五","richness":"富裕","output":37.2},{"planet":"BWI1-9 七","richness":"完美","output":35.27},{"planet":"C-LBQS 九","richness":"富裕","output":33.07},{"planet":"5-P1Y2 十三","richness":"富裕","output":31.95},{"planet":"J52-BH 三","richness":"富裕","output":31.13},{"planet":"C-LBQS 六","richness":"富裕","output":30.84},{"planet":"J52-BH 二","richness":"富裕","output":30.53},{"planet":"5-P1Y2 六","richness":"中等","output":27.8},{"planet":"5-P1Y2 十","richness":"中等","output":26.9},{"planet":"5-P1Y2 四","richness":"中等","output":24.43},{"planet":"C-LBQS 十一","richness":"中等","output":23.85},{"planet":"C-LBQS 七","richness":"中等","output":21.78}]},"等离子体团":{"max_output":1.74,"count":10,"records":[{"planet":"BWI1-9 六","richness":"富裕","output":1.74},{"planet":"J52-BH 一","richness":"中等","output":1.73},{"planet":"5-P1Y2 七","richness":"中等","output":1.71},{"planet":"5-P1Y2 一","richness":"中等","output":1.48},{"planet":"SVB-RE 四","richness":"中等","output":1.42},{"planet":"C-LBQS 一","richness":"中等","output":1.38},{"planet":"SVB-RE 五","richness":"中等","output":1.31},{"planet":"5-P1Y2 二","richness":"贫瘠","output":1.25},{"planet":"KJ-QWL 三","richness":"贫瘠","output":1.19},{"planet":"SVB-RE 七","richness":"贫瘠","output":0.83}]},"悬浮等离子":{"max_output":121.94,"count":2,"records":[{"planet":"SVB-RE 六","richness":"完美","output":121.94},{"planet":"KJ-QWL 一","richness":"中等","output":84.11}]},"杂色复合物":{"max_output":20.55,"count":1,"records":[{"planet":"KJ-QWL 八","richness":"贫瘠","output":20.55}]},"闪光合金":{"max_output":26.36,"count":6,"records":[{"planet":"BWI1-9 三","richness":"中等","output":26.36},{"planet":"5-P1Y2 一","richness":"中等","output":26.3},{"planet":"SVB-RE 六","richness":"中等","output":24.63},{"planet":"5-P1Y2 三","richness":"中等","output":23.73},{"planet":"BWI1-9 六","richness":"贫瘠","output":19.27},{"planet":"BWI1-9 四","richness":"贫瘠","output":18.85}]},"同位素燃料":{"max_output":4.02,"count":6,"records":[{"planet":"BWI1-9 六","richness":"中等","output":4.02},{"planet":"KJ-QWL 二","richness":"中等","output":3.48},{"planet":"BWI1-9 一","richness":"中等","output":3.39},{"planet":"KJ-QWL 三","richness":"中等","output":3.2},{"planet":"C-LBQS 二","richness":"贫瘠","output":2.79},{"planet":"SVB-RE 一","richness":"贫瘠","output":2.09}]},"基础金属":{"max_output":11.07,"count":14,"records":[{"planet":"C-LBQS 四","richness":"完美","output":11.07},{"planet":"C-LBQS 七","richness":"富裕","output":9.1},{"planet":"J52-BH 四","richness":"富裕","output":8.17},{"planet":"KMQ4-V 四","richness":"富裕","output":8.11},{"planet":"BWI1-9 一","richness":"中等","output":6.12},{"planet":"KMQ4-V 七","richness":"中等","output":6.02},{"planet":"KJ-QWL 三","richness":"贫瘠","output":5.38},{"planet":"C-LBQS 三","richness":"贫瘠","output":5.34},{"planet":"KJ-QWL 六","richness":"贫瘠","output":5.05},{"planet":"KMQ4-V 八","richness":"贫瘠","output":4.81},{"planet":"5-P1Y2 七","richness":"贫瘠","output":4.54},{"planet":"C-LBQS 一","richness":"贫瘠","output":4.41},{"planet":"SVB-RE 二","richness":"贫瘠","output":4.21},{"planet":"BWI1-9 二","richness":"贫瘠","output":3.68}]},"聚芳酰胺":{"max_output":25.13,"count":9,"records":[{"planet":"5-P1Y2 十二","richness":"富裕","output":25.13},{"planet":"KJ-QWL 六","richness":"富裕","output":22.84},{"planet":"KMQ4-V 五","richness":"富裕","output":22.51},{"planet":"BWI1-9 三","richness":"富裕","output":22.0},{"planet":"J52-BH 三","richness":"富裕","output":21.23},{"planet":"C-LBQS 五","richness":"富裕","output":20.91},{"planet":"BWI1-9 七","richness":"富裕","output":19.71},{"planet":"J52-BH 二","richness":"中等","output":19.04},{"planet":"5-P1Y2 十","richness":"中等","output":18.02}]}}}